{
  "fields": [
    {
      "aggregatable": false,
      "custom": false,
      "defaultValue": null,
      "extraTypeInfo": null,
      "filterable": false,
      "groupable": false,
      "inlineHelpText": null,
      "label": "Change Event ID",
      "name": "Id",
      "nillable": true,
      "picklistValues": [],
      "referenceTo": [],
      "relationshipName": null,
      "sortable": false,
      "type": "id"
    },
    {
      "aggregatable": false,
      "custom": false,
      "defaultValue": null,
      "extraTypeInfo": null,
      "filterable": false,
      "groupable": false,
      "inlineHelpText": null,
      "label": "Replay ID",
      "name": "ReplayId",
      "nillable": true,
      "picklistValues": [],
      "referenceTo": [],
      "relationshipName": null,
      "sortable": false,
      "type": "string"
    },
    {
      "aggregatable": false,
      "custom": false,
      "defaultValue": null,
      "extraTypeInfo": null,
      "filterable": false,
      "groupable": false,
      "inlineHelpText": null,
      "label": "Change Event Header",
      "name": "ChangeEventHeader",
      "nillable": false,
      "picklistValues": [],
      "referenceTo": [],
      "relationshipName": null,
      "sortable": false,
      "type": "complexvalue"
    },
    {
      "aggregatable": false,
      "custom": false,
      "defaultValue": null,
      "extraTypeInfo": null,
      "filterable": false,
      "groupable": false,
      "inlineHelpText": null,
      "label": "Owner ID",
      "name": "OwnerId",
      "nillable": true,
      "picklistValues": [],
      "referenceTo": [
        "User"
      ],
      "relationshipName": null,
      "sortable": false,
      "type": "reference"
    },
    {
      "aggregatable": false,
      "custom": false,
      "defaultValue": null,
      "extraTypeInfo": null,
      "filterable": false,
      "groupable": false,
      "inlineHelpText": null,
      "label": "Name",
      "name": "Name",
      "nillable": true,
      "picklistValues": [],
      "referenceTo": [],
      "relationshipName": null,
      "sortable": false,
      "type": "string"
    },
    {
      "aggregatable": false,
      "custom": false,
      "defaultValue": null,
      "extraTypeInfo": null,
      "filterable": false,
      "groupable": false,
      "inlineHelpText": null,
      "label": "Created Date",
      "name": "CreatedDate",
      "nillable": true,
      "picklistValues": [],
      "referenceTo": [],
      "relationshipName": null,
      "sortable": false,
      "type": "datetime"
    },
    {
      "aggregatable": false,
      "custom": false,
      "defaultValue": null,
      "extraTypeInfo": null,
      "filterable": false,
      "groupable": false,
      "inlineHelpText": null,
      "label": "Created By ID",
      "name": "CreatedById",
      "nillable": true,
      "picklistValues": [],
      "referenceTo": [
        "User"
      ],
      "relationshipName": null,
      "sortable": false,
      "type": "reference"
    },
    {
      "aggregatable": false,
      "custom": false,
      "defaultValue": null,
      "extraTypeInfo": null,
      "filterable": false,
      "groupable": false,
      "inlineHelpText": null,
      "label": "Last Modified Date",
      "name": "LastModifiedDate",
      "nillable": true,
      "picklistValues": [],
      "referenceTo": [],
      "relationshipName": null,
      "sortable": false,
      "type": "datetime"
    },
    {
      "aggregatable": false,
      "custom": false,
      "defaultValue": null,
      "extraTypeInfo": null,
      "filterable": false,
      "groupable": false,
      "inlineHelpText": null,
      "label": "Last Modified By ID",
      "name": "LastModifiedById",
      "nillable": true,
      "picklistValues": [],
      "referenceTo": [
        "User"
      ],
      "relationshipName": null,
      "sortable": false,
      "type": "reference"
    },
    {
      "aggregatable": false,
      "custom": false,
      "defaultValue": null,
      "extraTypeInfo": null,
      "filterable": false,
      "groupable": false,
      "inlineHelpText": null,
      "label": "Party ID",
      "name": "PartyId",
      "nillable": true,
      "picklistValues": [],
      "referenceTo": [
        "Individual"
      ],
      "relationshipName": null,
      "sortable": false,
      "type": "reference"
    },
    {
      "aggregatable": false,
      "custom": false,
      "defaultValue": null,
      "extraTypeInfo": null,
      "filterable": false,
      "groupable": false,
      "inlineHelpText": null,
      "label": "Contact Point Type ID",
      "name": "ContactPointType",
      "nillable": true,
      "picklistValues": [
        {
          "active": true,
          "defaultValue": false,
          "label": "Email",
          "validFor": null,
          "value": "Email"
        },
        {
          "active": true,
          "defaultValue": false,
          "label": "Phone",
          "validFor": null,
          "value": "Phone"
        },
        {
          "active": true,
          "defaultValue": false,
          "label": "Web",
          "validFor": null,
          "value": "Web"
        },
        {
          "active": true,
          "defaultValue": false,
          "label": "Social",
          "validFor": null,
          "value": "Social"
        },
        {
          "active": true,
          "defaultValue": false,
          "label": "Mailing Address",
          "validFor": null,
          "value": "MailingAddress"
        },
        {
          "active": true,
          "defaultValue": false,
          "label": "In Person",
          "validFor": null,
          "value": "InPerson"
        },
        {
          "active": true,
          "defaultValue": false,
          "label": "Video",
          "validFor": null,
          "value": "Video"
        }
      ],
      "referenceTo": [],
      "relationshipName": null,
      "sortable": false,
      "type": "picklist"
    },
    {
      "aggregatable": false,
      "custom": false,
      "defaultValue": null,
      "extraTypeInfo": null,
      "filterable": false,
      "groupable": false,
      "inlineHelpText": null,
      "label": "Data Use Purpose ID",
      "name": "DataUsePurposeId",
      "nillable": true,
      "picklistValues": [],
      "referenceTo": [
        "DataUsePurpose"
      ],
      "relationshipName": null,
      "sortable": false,
      "type": "reference"
    },
    {
      "aggregatable": false,
      "custom": false,
      "defaultValue": "NotSeen",
      "extraTypeInfo": null,
      "filterable": false,
      "groupable": false,
      "inlineHelpText": null,
      "label": "Privacy Consent Status",
      "name": "PrivacyConsentStatus",
      "nillable": true,
      "picklistValues": [
        {
          "active": true,
          "defaultValue": true,
          "label": "Not Seen",
          "validFor": null,
          "value": "NotSeen"
        },
        {
          "active": true,
          "defaultValue": false,
          "label": "Seen",
          "validFor": null,
          "value": "Seen"
        },
        {
          "active": true,
          "defaultValue": false,
          "label": "Opt In",
          "validFor": null,
          "value": "OptIn"
        },
        {
          "active": true,
          "defaultValue": false,
          "label": "Opt Out",
          "validFor": null,
          "value": "OptOut"
        },
        {
          "active": true,
          "defaultValue": false,
          "label": "Opt In Pending",
          "validFor": null,
          "value": "OptInPending"
        },
        {
          "active": true,
          "defaultValue": false,
          "label": "Opt Out Pending",
          "validFor": null,
          "value": "OptOutPending"
        }
      ],
      "referenceTo": [],
      "relationshipName": null,
      "sortable": false,
      "type": "picklist"
    },
    {
      "aggregatable": false,
      "custom": false,
      "defaultValue": null,
      "extraTypeInfo": null,
      "filterable": false,
      "groupable": false,
      "inlineHelpText": null,
      "label": "Effective From",
      "name": "EffectiveFrom",
      "nillable": true,
      "picklistValues": [],
      "referenceTo": [],
      "relationshipName": null,
      "sortable": false,
      "type": "datetime"
    },
    {
      "aggregatable": false,
      "custom": false,
      "defaultValue": null,
      "extraTypeInfo": null,
      "filterable": false,
      "groupable": false,
      "inlineHelpText": null,
      "label": "Effective To ",
      "name": "EffectiveTo",
      "nillable": true,
      "picklistValues": [],
      "referenceTo": [],
      "relationshipName": null,
      "sortable": false,
      "type": "datetime"
    },
    {
      "aggregatable": false,
      "custom": false,
      "defaultValue": null,
      "extraTypeInfo": null,
      "filterable": false,
      "groupable": false,
      "inlineHelpText": null,
      "label": "Capture Date",
      "name": "CaptureDate",
      "nillable": true,
      "picklistValues": [],
      "referenceTo": [],
      "relationshipName": null,
      "sortable": false,
      "type": "datetime"
    },
    {
      "aggregatable": false,
      "custom": false,
      "defaultValue": null,
      "extraTypeInfo": null,
      "filterable": false,
      "groupable": false,
      "inlineHelpText": null,
      "label": "Capture Contact Point Type",
      "name": "CaptureContactPointType",
      "nillable": true,
      "picklistValues": [
        {
          "active": true,
          "defaultValue": false,
          "label": "Email",
          "validFor": null,
          "value": "Email"
        },
        {
          "active": true,
          "defaultValue": false,
          "label": "Phone",
          "validFor": null,
          "value": "Phone"
        },
        {
          "active": true,
          "defaultValue": false,
          "label": "Web",
          "validFor": null,
          "value": "Web"
        },
        {
          "active": true,
          "defaultValue": false,
          "label": "Social",
          "validFor": null,
          "value": "Social"
        },
        {
          "active": true,
          "defaultValue": false,
          "label": "Mailing Address",
          "validFor": null,
          "value": "MailingAddress"
        },
        {
          "active": true,
          "defaultValue": false,
          "label": "In Person",
          "validFor": null,
          "value": "InPerson"
        },
        {
          "active": true,
          "defaultValue": false,
          "label": "Video",
          "validFor": null,
          "value": "Video"
        }
      ],
      "referenceTo": [],
      "relationshipName": null,
      "sortable": false,
      "type": "picklist"
    },
    {
      "aggregatable": false,
      "custom": false,
      "defaultValue": null,
      "extraTypeInfo": null,
      "filterable": false,
      "groupable": false,
      "inlineHelpText": null,
      "label": "Capture Source",
      "name": "CaptureSource",
      "nillable": true,
      "picklistValues": [],
      "referenceTo": [],
      "relationshipName": null,
      "sortable": false,
      "type": "string"
    },
    {
      "aggregatable": false,
      "custom": false,
      "defaultValue": null,
      "extraTypeInfo": null,
      "filterable": false,
      "groupable": false,
      "inlineHelpText": null,
      "label": "Double Consent Capture Date",
      "name": "DoubleConsentCaptureDate",
      "nillable": true,
      "picklistValues": [],
      "referenceTo": [],
      "relationshipName": null,
      "sortable": false,
      "type": "datetime"
    },
    {
      "aggregatable": false,
      "custom": false,
      "defaultValue": null,
      "extraTypeInfo": null,
      "filterable": false,
      "groupable": false,
      "inlineHelpText": null,
      "label": "Party Role ID",
      "name": "PartyRoleId",
      "nillable": true,
      "picklistValues": [],
      "referenceTo": [
        "Customer",
        "Seller"
      ],
      "relationshipName": null,
      "sortable": false,
      "type": "reference"
    },
    {
      "aggregatable": false,
      "custom": false,
      "defaultValue": null,
      "extraTypeInfo": null,
      "filterable": false,
      "groupable": false,
      "inlineHelpText": null,
      "label": "Business Brand ID",
      "name": "BusinessBrandId",
      "nillable": true,
      "picklistValues": [],
      "referenceTo": [
        "BusinessBrand"
      ],
      "relationshipName": null,
      "sortable": false,
      "type": "reference"
    }
  ],
  "label": "Contact Point Type Consent Change Event",
  "childRelationships": [],
  "custom": false,
  "name": "ContactPointTypeConsentChangeEvent",
  "queryable": false
}