{
  "fields": [
    {
      "aggregatable": true,
      "custom": false,
      "defaultValue": null,
      "extraTypeInfo": null,
      "filterable": true,
      "groupable": true,
      "inlineHelpText": null,
      "label": "Contact History ID",
      "name": "Id",
      "nillable": false,
      "picklistValues": [],
      "referenceTo": [],
      "relationshipName": null,
      "sortable": true,
      "type": "id"
    },
    {
      "aggregatable": false,
      "custom": false,
      "defaultValue": false,
      "extraTypeInfo": null,
      "filterable": true,
      "groupable": true,
      "inlineHelpText": null,
      "label": "Deleted",
      "name": "IsDeleted",
      "nillable": false,
      "picklistValues": [],
      "referenceTo": [],
      "relationshipName": null,
      "sortable": true,
      "type": "boolean"
    },
    {
      "aggregatable": true,
      "custom": false,
      "defaultValue": null,
      "extraTypeInfo": null,
      "filterable": true,
      "groupable": true,
      "inlineHelpText": null,
      "label": "Contact ID",
      "name": "ContactId",
      "nillable": false,
      "picklistValues": [],
      "referenceTo": [
        "Contact"
      ],
      "relationshipName": "Contact",
      "sortable": true,
      "type": "reference"
    },
    {
      "aggregatable": true,
      "custom": false,
      "defaultValue": null,
      "extraTypeInfo": null,
      "filterable": true,
      "groupable": true,
      "inlineHelpText": null,
      "label": "Created By ID",
      "name": "CreatedById",
      "nillable": false,
      "picklistValues": [],
      "referenceTo": [
        "User"
      ],
      "relationshipName": "CreatedBy",
      "sortable": true,
      "type": "reference"
    },
    {
      "aggregatable": true,
      "custom": false,
      "defaultValue": null,
      "extraTypeInfo": null,
      "filterable": true,
      "groupable": false,
      "inlineHelpText": null,
      "label": "Created Date",
      "name": "CreatedDate",
      "nillable": false,
      "picklistValues": [],
      "referenceTo": [],
      "relationshipName": null,
      "sortable": true,
      "type": "datetime"
    },
    {
      "aggregatable": true,
      "custom": false,
      "defaultValue": null,
      "extraTypeInfo": null,
      "filterable": true,
      "groupable": true,
      "inlineHelpText": null,
      "label": "Changed Field",
      "name": "Field",
      "nillable": false,
      "picklistValues": [
        {
          "active": true,
          "defaultValue": false,
          "label": "Account Name",
          "validFor": null,
          "value": "Account"
        },
        {
          "active": true,
          "defaultValue": false,
          "label": "Assistant",
          "validFor": null,
          "value": "AssistantName"
        },
        {
          "active": true,
          "defaultValue": false,
          "label": "Asst. Phone",
          "validFor": null,
          "value": "AssistantPhone"
        },
        {
          "active": true,
          "defaultValue": false,
          "label": "Birthdate",
          "validFor": null,
          "value": "Birthdate"
        },
        {
          "active": true,
          "defaultValue": false,
          "label": "Contact Merged",
          "validFor": null,
          "value": "contactMerged"
        },
        {
          "active": true,
          "defaultValue": false,
          "label": "Contact Owner",
          "validFor": null,
          "value": "Owner"
        },
        {
          "active": true,
          "defaultValue": false,
          "label": "Created.",
          "validFor": null,
          "value": "created"
        },
        {
          "active": true,
          "defaultValue": false,
          "label": "Created by lead convert",
          "validFor": null,
          "value": "contactCreatedFromLead"
        },
        {
          "active": true,
          "defaultValue": false,
          "label": "Creation Source",
          "validFor": null,
          "value": "ContactSource"
        },
        {
          "active": true,
          "defaultValue": false,
          "label": "Custom Person Merged",
          "validFor": null,
          "value": "customPersonMerged"
        },
        {
          "active": true,
          "defaultValue": false,
          "label": "Data.com Key",
          "validFor": null,
          "value": "Jigsaw"
        },
        {
          "active": true,
          "defaultValue": false,
          "label": "Department",
          "validFor": null,
          "value": "Department"
        },
        {
          "active": true,
          "defaultValue": false,
          "label": "Description",
          "validFor": null,
          "value": "Description"
        },
        {
          "active": true,
          "defaultValue": false,
          "label": "Do Not Call",
          "validFor": null,
          "value": "DoNotCall"
        },
        {
          "active": true,
          "defaultValue": false,
          "label": "Email",
          "validFor": null,
          "value": "Email"
        },
        {
          "active": true,
          "defaultValue": false,
          "label": "Email Bounced Date",
          "validFor": null,
          "value": "EmailBouncedDate"
        },
        {
          "active": true,
          "defaultValue": false,
          "label": "Email Bounced Reason",
          "validFor": null,
          "value": "EmailBouncedReason"
        },
        {
          "active": true,
          "defaultValue": false,
          "label": "Email Opt Out",
          "validFor": null,
          "value": "HasOptedOutOfEmail"
        },
        {
          "active": true,
          "defaultValue": false,
          "label": "Fax",
          "validFor": null,
          "value": "Fax"
        },
        {
          "active": true,
          "defaultValue": false,
          "label": "Fax Opt Out",
          "validFor": null,
          "value": "HasOptedOutOfFax"
        },
        {
          "active": true,
          "defaultValue": false,
          "label": "Feed event",
          "validFor": null,
          "value": "feedEvent"
        },
        {
          "active": true,
          "defaultValue": false,
          "label": "First Name",
          "validFor": null,
          "value": "FirstName"
        },
        {
          "active": true,
          "defaultValue": false,
          "label": "Gender Identity",
          "validFor": null,
          "value": "GenderIdentity"
        },
        {
          "active": true,
          "defaultValue": false,
          "label": "Home Phone",
          "validFor": null,
          "value": "HomePhone"
        },
        {
          "active": true,
          "defaultValue": false,
          "label": "Individual",
          "validFor": null,
          "value": "Individual"
        },
        {
          "active": true,
          "defaultValue": false,
          "label": "Individual Merged",
          "validFor": null,
          "value": "individualMerged"
        },
        {
          "active": true,
          "defaultValue": false,
          "label": "Languages",
          "validFor": null,
          "value": "Languages__c"
        },
        {
          "active": true,
          "defaultValue": false,
          "label": "Last Name",
          "validFor": null,
          "value": "LastName"
        },
        {
          "active": true,
          "defaultValue": false,
          "label": "Lead converted to Contact",
          "validFor": null,
          "value": "contactUpdatedByLead"
        },
        {
          "active": true,
          "defaultValue": false,
          "label": "Lead Source",
          "validFor": null,
          "value": "LeadSource"
        },
        {
          "active": true,
          "defaultValue": false,
          "label": "Level",
          "validFor": null,
          "value": "Level__c"
        },
        {
          "active": true,
          "defaultValue": false,
          "label": "Mailing Address",
          "validFor": null,
          "value": "MailingAddress"
        },
        {
          "active": true,
          "defaultValue": false,
          "label": "Mailing City",
          "validFor": null,
          "value": "MailingCity"
        },
        {
          "active": true,
          "defaultValue": false,
          "label": "Mailing Country",
          "validFor": null,
          "value": "MailingCountry"
        },
        {
          "active": true,
          "defaultValue": false,
          "label": "Mailing Geocode Accuracy",
          "validFor": null,
          "value": "MailingGeocodeAccuracy"
        },
        {
          "active": true,
          "defaultValue": false,
          "label": "Mailing Latitude",
          "validFor": null,
          "value": "MailingLatitude"
        },
        {
          "active": true,
          "defaultValue": false,
          "label": "Mailing Longitude",
          "validFor": null,
          "value": "MailingLongitude"
        },
        {
          "active": true,
          "defaultValue": false,
          "label": "Mailing State/Province",
          "validFor": null,
          "value": "MailingState"
        },
        {
          "active": true,
          "defaultValue": false,
          "label": "Mailing Street",
          "validFor": null,
          "value": "MailingStreet"
        },
        {
          "active": true,
          "defaultValue": false,
          "label": "Mailing Zip/Postal Code",
          "validFor": null,
          "value": "MailingPostalCode"
        },
        {
          "active": true,
          "defaultValue": false,
          "label": "Mobile",
          "validFor": null,
          "value": "MobilePhone"
        },
        {
          "active": true,
          "defaultValue": false,
          "label": "Name",
          "validFor": null,
          "value": "Name"
        },
        {
          "active": true,
          "defaultValue": false,
          "label": "Other Address",
          "validFor": null,
          "value": "OtherAddress"
        },
        {
          "active": true,
          "defaultValue": false,
          "label": "Other City",
          "validFor": null,
          "value": "OtherCity"
        },
        {
          "active": true,
          "defaultValue": false,
          "label": "Other Country",
          "validFor": null,
          "value": "OtherCountry"
        },
        {
          "active": true,
          "defaultValue": false,
          "label": "Other Geocode Accuracy",
          "validFor": null,
          "value": "OtherGeocodeAccuracy"
        },
        {
          "active": true,
          "defaultValue": false,
          "label": "Other Latitude",
          "validFor": null,
          "value": "OtherLatitude"
        },
        {
          "active": true,
          "defaultValue": false,
          "label": "Other Longitude",
          "validFor": null,
          "value": "OtherLongitude"
        },
        {
          "active": true,
          "defaultValue": false,
          "label": "Other Phone",
          "validFor": null,
          "value": "OtherPhone"
        },
        {
          "active": true,
          "defaultValue": false,
          "label": "Other State/Province",
          "validFor": null,
          "value": "OtherState"
        },
        {
          "active": true,
          "defaultValue": false,
          "label": "Other Street",
          "validFor": null,
          "value": "OtherStreet"
        },
        {
          "active": true,
          "defaultValue": false,
          "label": "Other Zip/Postal Code",
          "validFor": null,
          "value": "OtherPostalCode"
        },
        {
          "active": true,
          "defaultValue": false,
          "label": "Owner (Accepted)",
          "validFor": null,
          "value": "ownerAccepted"
        },
        {
          "active": true,
          "defaultValue": false,
          "label": "Owner (Assignment)",
          "validFor": null,
          "value": "ownerAssignment"
        },
        {
          "active": true,
          "defaultValue": false,
          "label": "Phone",
          "validFor": null,
          "value": "Phone"
        },
        {
          "active": true,
          "defaultValue": false,
          "label": "Pronouns",
          "validFor": null,
          "value": "Pronouns"
        },
        {
          "active": true,
          "defaultValue": false,
          "label": "Record locked.",
          "validFor": null,
          "value": "locked"
        },
        {
          "active": true,
          "defaultValue": false,
          "label": "Record unlocked.",
          "validFor": null,
          "value": "unlocked"
        },
        {
          "active": true,
          "defaultValue": false,
          "label": "Reports To",
          "validFor": null,
          "value": "ReportsTo"
        },
        {
          "active": true,
          "defaultValue": false,
          "label": "Salutation",
          "validFor": null,
          "value": "Salutation"
        },
        {
          "active": true,
          "defaultValue": false,
          "label": "Title",
          "validFor": null,
          "value": "Title"
        }
      ],
      "referenceTo": [],
      "relationshipName": null,
      "sortable": true,
      "type": "picklist"
    },
    {
      "aggregatable": true,
      "custom": false,
      "defaultValue": null,
      "extraTypeInfo": null,
      "filterable": true,
      "groupable": true,
      "inlineHelpText": null,
      "label": "Datatype",
      "name": "DataType",
      "nillable": true,
      "picklistValues": [
        {
          "active": true,
          "defaultValue": false,
          "label": null,
          "validFor": null,
          "value": "Address"
        },
        {
          "active": true,
          "defaultValue": false,
          "label": null,
          "validFor": null,
          "value": "AnyType"
        },
        {
          "active": true,
          "defaultValue": false,
          "label": null,
          "validFor": null,
          "value": "AutoNumber"
        },
        {
          "active": true,
          "defaultValue": false,
          "label": null,
          "validFor": null,
          "value": "Base64"
        },
        {
          "active": true,
          "defaultValue": false,
          "label": null,
          "validFor": null,
          "value": "BitVector"
        },
        {
          "active": true,
          "defaultValue": false,
          "label": null,
          "validFor": null,
          "value": "Boolean"
        },
        {
          "active": true,
          "defaultValue": false,
          "label": null,
          "validFor": null,
          "value": "Content"
        },
        {
          "active": true,
          "defaultValue": false,
          "label": null,
          "validFor": null,
          "value": "Currency"
        },
        {
          "active": true,
          "defaultValue": false,
          "label": null,
          "validFor": null,
          "value": "DataCategoryGroupReference"
        },
        {
          "active": true,
          "defaultValue": false,
          "label": null,
          "validFor": null,
          "value": "DateOnly"
        },
        {
          "active": true,
          "defaultValue": false,
          "label": null,
          "validFor": null,
          "value": "DateTime"
        },
        {
          "active": true,
          "defaultValue": false,
          "label": null,
          "validFor": null,
          "value": "Division"
        },
        {
          "active": true,
          "defaultValue": false,
          "label": null,
          "validFor": null,
          "value": "Double"
        },
        {
          "active": true,
          "defaultValue": false,
          "label": null,
          "validFor": null,
          "value": "DynamicEnum"
        },
        {
          "active": true,
          "defaultValue": false,
          "label": null,
          "validFor": null,
          "value": "Email"
        },
        {
          "active": true,
          "defaultValue": false,
          "label": null,
          "validFor": null,
          "value": "EncryptedBase64"
        },
        {
          "active": true,
          "defaultValue": false,
          "label": null,
          "validFor": null,
          "value": "EncryptedText"
        },
        {
          "active": true,
          "defaultValue": false,
          "label": null,
          "validFor": null,
          "value": "EntityId"
        },
        {
          "active": true,
          "defaultValue": false,
          "label": null,
          "validFor": null,
          "value": "EnumOrId"
        },
        {
          "active": true,
          "defaultValue": false,
          "label": null,
          "validFor": null,
          "value": "ExternalId"
        },
        {
          "active": true,
          "defaultValue": false,
          "label": null,
          "validFor": null,
          "value": "Fax"
        },
        {
          "active": true,
          "defaultValue": false,
          "label": null,
          "validFor": null,
          "value": "File"
        },
        {
          "active": true,
          "defaultValue": false,
          "label": null,
          "validFor": null,
          "value": "HtmlMultiLineText"
        },
        {
          "active": true,
          "defaultValue": false,
          "label": null,
          "validFor": null,
          "value": "HtmlStringPlusClob"
        },
        {
          "active": true,
          "defaultValue": false,
          "label": null,
          "validFor": null,
          "value": "InetAddress"
        },
        {
          "active": true,
          "defaultValue": false,
          "label": null,
          "validFor": null,
          "value": "Json"
        },
        {
          "active": true,
          "defaultValue": false,
          "label": null,
          "validFor": null,
          "value": "Location"
        },
        {
          "active": true,
          "defaultValue": false,
          "label": null,
          "validFor": null,
          "value": "MultiEnum"
        },
        {
          "active": true,
          "defaultValue": false,
          "label": null,
          "validFor": null,
          "value": "MultiLineText"
        },
        {
          "active": true,
          "defaultValue": false,
          "label": null,
          "validFor": null,
          "value": "Namespace"
        },
        {
          "active": true,
          "defaultValue": false,
          "label": null,
          "validFor": null,
          "value": "Percent"
        },
        {
          "active": true,
          "defaultValue": false,
          "label": null,
          "validFor": null,
          "value": "PersonName"
        },
        {
          "active": true,
          "defaultValue": false,
          "label": null,
          "validFor": null,
          "value": "Phone"
        },
        {
          "active": true,
          "defaultValue": false,
          "label": null,
          "validFor": null,
          "value": "Raw"
        },
        {
          "active": true,
          "defaultValue": false,
          "label": null,
          "validFor": null,
          "value": "RecordType"
        },
        {
          "active": true,
          "defaultValue": false,
          "label": null,
          "validFor": null,
          "value": "SfdcEncryptedText"
        },
        {
          "active": true,
          "defaultValue": false,
          "label": null,
          "validFor": null,
          "value": "SimpleNamespace"
        },
        {
          "active": true,
          "defaultValue": false,
          "label": null,
          "validFor": null,
          "value": "StringPlusClob"
        },
        {
          "active": true,
          "defaultValue": false,
          "label": null,
          "validFor": null,
          "value": "Switchable_PersonName"
        },
        {
          "active": true,
          "defaultValue": false,
          "label": null,
          "validFor": null,
          "value": "Text"
        },
        {
          "active": true,
          "defaultValue": false,
          "label": null,
          "validFor": null,
          "value": "TimeOnly"
        },
        {
          "active": true,
          "defaultValue": false,
          "label": null,
          "validFor": null,
          "value": "Url"
        },
        {
          "active": true,
          "defaultValue": false,
          "label": null,
          "validFor": null,
          "value": "YearQuarter"
        }
      ],
      "referenceTo": [],
      "relationshipName": null,
      "sortable": true,
      "type": "picklist"
    },
    {
      "aggregatable": false,
      "custom": false,
      "defaultValue": null,
      "extraTypeInfo": null,
      "filterable": false,
      "groupable": false,
      "inlineHelpText": null,
      "label": "Old Value",
      "name": "OldValue",
      "nillable": true,
      "picklistValues": [],
      "referenceTo": [],
      "relationshipName": null,
      "sortable": true,
      "type": "anyType"
    },
    {
      "aggregatable": false,
      "custom": false,
      "defaultValue": null,
      "extraTypeInfo": null,
      "filterable": false,
      "groupable": false,
      "inlineHelpText": null,
      "label": "New Value",
      "name": "NewValue",
      "nillable": true,
      "picklistValues": [],
      "referenceTo": [],
      "relationshipName": null,
      "sortable": true,
      "type": "anyType"
    }
  ],
  "label": "Contact History",
  "childRelationships": [],
  "custom": false,
  "name": "ContactHistory",
  "queryable": true
}