{
  "fields": [
    {
      "aggregatable": true,
      "custom": false,
      "defaultValue": null,
      "extraTypeInfo": null,
      "filterable": true,
      "groupable": true,
      "inlineHelpText": null,
      "label": "Omni Data Transformation Item ID",
      "name": "Id",
      "nillable": false,
      "picklistValues": [],
      "referenceTo": [],
      "relationshipName": null,
      "sortable": true,
      "type": "id"
    },
    {
      "aggregatable": false,
      "custom": false,
      "defaultValue": false,
      "extraTypeInfo": null,
      "filterable": true,
      "groupable": true,
      "inlineHelpText": null,
      "label": "Deleted",
      "name": "IsDeleted",
      "nillable": false,
      "picklistValues": [],
      "referenceTo": [],
      "relationshipName": null,
      "sortable": true,
      "type": "boolean"
    },
    {
      "aggregatable": true,
      "custom": false,
      "defaultValue": null,
      "extraTypeInfo": null,
      "filterable": true,
      "groupable": true,
      "inlineHelpText": null,
      "label": "Omni Data Transformation API Name",
      "name": "Name",
      "nillable": false,
      "picklistValues": [],
      "referenceTo": [],
      "relationshipName": null,
      "sortable": true,
      "type": "string"
    },
    {
      "aggregatable": true,
      "custom": false,
      "defaultValue": null,
      "extraTypeInfo": null,
      "filterable": true,
      "groupable": false,
      "inlineHelpText": null,
      "label": "Created Date",
      "name": "CreatedDate",
      "nillable": false,
      "picklistValues": [],
      "referenceTo": [],
      "relationshipName": null,
      "sortable": true,
      "type": "datetime"
    },
    {
      "aggregatable": true,
      "custom": false,
      "defaultValue": null,
      "extraTypeInfo": null,
      "filterable": true,
      "groupable": true,
      "inlineHelpText": null,
      "label": "Created By ID",
      "name": "CreatedById",
      "nillable": false,
      "picklistValues": [],
      "referenceTo": [
        "User"
      ],
      "relationshipName": "CreatedBy",
      "sortable": true,
      "type": "reference"
    },
    {
      "aggregatable": true,
      "custom": false,
      "defaultValue": null,
      "extraTypeInfo": null,
      "filterable": true,
      "groupable": false,
      "inlineHelpText": null,
      "label": "Last Modified Date",
      "name": "LastModifiedDate",
      "nillable": false,
      "picklistValues": [],
      "referenceTo": [],
      "relationshipName": null,
      "sortable": true,
      "type": "datetime"
    },
    {
      "aggregatable": true,
      "custom": false,
      "defaultValue": null,
      "extraTypeInfo": null,
      "filterable": true,
      "groupable": true,
      "inlineHelpText": null,
      "label": "Last Modified By ID",
      "name": "LastModifiedById",
      "nillable": false,
      "picklistValues": [],
      "referenceTo": [
        "User"
      ],
      "relationshipName": "LastModifiedBy",
      "sortable": true,
      "type": "reference"
    },
    {
      "aggregatable": true,
      "custom": false,
      "defaultValue": null,
      "extraTypeInfo": null,
      "filterable": true,
      "groupable": false,
      "inlineHelpText": null,
      "label": "System Modstamp",
      "name": "SystemModstamp",
      "nillable": false,
      "picklistValues": [],
      "referenceTo": [],
      "relationshipName": null,
      "sortable": true,
      "type": "datetime"
    },
    {
      "aggregatable": true,
      "custom": false,
      "defaultValue": null,
      "extraTypeInfo": null,
      "filterable": true,
      "groupable": false,
      "inlineHelpText": null,
      "label": "Last Viewed Date",
      "name": "LastViewedDate",
      "nillable": true,
      "picklistValues": [],
      "referenceTo": [],
      "relationshipName": null,
      "sortable": true,
      "type": "datetime"
    },
    {
      "aggregatable": true,
      "custom": false,
      "defaultValue": null,
      "extraTypeInfo": null,
      "filterable": true,
      "groupable": false,
      "inlineHelpText": null,
      "label": "Last Referenced Date",
      "name": "LastReferencedDate",
      "nillable": true,
      "picklistValues": [],
      "referenceTo": [],
      "relationshipName": null,
      "sortable": true,
      "type": "datetime"
    },
    {
      "aggregatable": true,
      "custom": false,
      "defaultValue": null,
      "extraTypeInfo": null,
      "filterable": true,
      "groupable": true,
      "inlineHelpText": null,
      "label": "Omni Data Transformations ID",
      "name": "OmniDataTransformationId",
      "nillable": false,
      "picklistValues": [],
      "referenceTo": [
        "OmniDataTransform"
      ],
      "relationshipName": "OmniDataTransformation",
      "sortable": true,
      "type": "reference"
    },
    {
      "aggregatable": false,
      "custom": false,
      "defaultValue": null,
      "extraTypeInfo": "plaintextarea",
      "filterable": false,
      "groupable": false,
      "inlineHelpText": null,
      "label": "Default Value",
      "name": "DefaultValue",
      "nillable": true,
      "picklistValues": [],
      "referenceTo": [],
      "relationshipName": null,
      "sortable": false,
      "type": "textarea"
    },
    {
      "aggregatable": true,
      "custom": false,
      "defaultValue": null,
      "extraTypeInfo": null,
      "filterable": true,
      "groupable": true,
      "inlineHelpText": null,
      "label": "Filter Data Type",
      "name": "FilterDataType",
      "nillable": true,
      "picklistValues": [
        {
          "active": true,
          "defaultValue": false,
          "label": "ADDRESS",
          "validFor": null,
          "value": "ADDRESS"
        },
        {
          "active": true,
          "defaultValue": false,
          "label": "ANYTYPE",
          "validFor": null,
          "value": "ANYTYPE"
        },
        {
          "active": true,
          "defaultValue": false,
          "label": "BASE64",
          "validFor": null,
          "value": "BASE64"
        },
        {
          "active": true,
          "defaultValue": false,
          "label": "BOOLEAN",
          "validFor": null,
          "value": "BOOLEAN"
        },
        {
          "active": true,
          "defaultValue": false,
          "label": "COMBOBOX",
          "validFor": null,
          "value": "COMBOBOX"
        },
        {
          "active": true,
          "defaultValue": false,
          "label": "CURRENCY",
          "validFor": null,
          "value": "CURRENCY"
        },
        {
          "active": true,
          "defaultValue": false,
          "label": "DATACATEGORY",
          "validFor": null,
          "value": "DATACATEGORY"
        },
        {
          "active": true,
          "defaultValue": false,
          "label": "GROUPREFERENCE",
          "validFor": null,
          "value": "GROUPREFERENCE"
        },
        {
          "active": true,
          "defaultValue": false,
          "label": "DATE",
          "validFor": null,
          "value": "DATE"
        },
        {
          "active": true,
          "defaultValue": false,
          "label": "DATETIME",
          "validFor": null,
          "value": "DATETIME"
        },
        {
          "active": true,
          "defaultValue": false,
          "label": "DOUBLE",
          "validFor": null,
          "value": "DOUBLE"
        },
        {
          "active": true,
          "defaultValue": false,
          "label": "EMAIL",
          "validFor": null,
          "value": "EMAIL"
        },
        {
          "active": true,
          "defaultValue": false,
          "label": "ENCRYPTEDSTRING",
          "validFor": null,
          "value": "ENCRYPTEDSTRING"
        },
        {
          "active": true,
          "defaultValue": false,
          "label": "ID",
          "validFor": null,
          "value": "ID"
        },
        {
          "active": true,
          "defaultValue": false,
          "label": "INTEGER",
          "validFor": null,
          "value": "INTEGER"
        },
        {
          "active": true,
          "defaultValue": false,
          "label": "LONG",
          "validFor": null,
          "value": "LONG"
        },
        {
          "active": true,
          "defaultValue": false,
          "label": "MULTIPICKLIST",
          "validFor": null,
          "value": "MULTIPICKLIST"
        },
        {
          "active": true,
          "defaultValue": false,
          "label": "PERCENT",
          "validFor": null,
          "value": "PERCENT"
        },
        {
          "active": true,
          "defaultValue": false,
          "label": "PHONE",
          "validFor": null,
          "value": "PHONE"
        },
        {
          "active": true,
          "defaultValue": false,
          "label": "PICKLIST",
          "validFor": null,
          "value": "PICKLIST"
        },
        {
          "active": true,
          "defaultValue": false,
          "label": "REFERENCE",
          "validFor": null,
          "value": "REFERENCE"
        },
        {
          "active": true,
          "defaultValue": false,
          "label": "STRING",
          "validFor": null,
          "value": "STRING"
        },
        {
          "active": true,
          "defaultValue": false,
          "label": "TEXTAREA",
          "validFor": null,
          "value": "TEXTAREA"
        },
        {
          "active": true,
          "defaultValue": false,
          "label": "TIME",
          "validFor": null,
          "value": "TIME"
        },
        {
          "active": true,
          "defaultValue": false,
          "label": "URL",
          "validFor": null,
          "value": "URL"
        }
      ],
      "referenceTo": [],
      "relationshipName": null,
      "sortable": true,
      "type": "picklist"
    },
    {
      "aggregatable": true,
      "custom": false,
      "defaultValue": null,
      "extraTypeInfo": null,
      "filterable": true,
      "groupable": false,
      "inlineHelpText": null,
      "label": "Filter Group",
      "name": "FilterGroup",
      "nillable": true,
      "picklistValues": [],
      "referenceTo": [],
      "relationshipName": null,
      "sortable": true,
      "type": "double"
    },
    {
      "aggregatable": true,
      "custom": false,
      "defaultValue": null,
      "extraTypeInfo": null,
      "filterable": true,
      "groupable": true,
      "inlineHelpText": null,
      "label": "Filter Operator",
      "name": "FilterOperator",
      "nillable": true,
      "picklistValues": [
        {
          "active": true,
          "defaultValue": false,
          "label": "=",
          "validFor": null,
          "value": "="
        },
        {
          "active": true,
          "defaultValue": false,
          "label": "<>",
          "validFor": null,
          "value": "<>"
        },
        {
          "active": true,
          "defaultValue": false,
          "label": "<",
          "validFor": null,
          "value": "<"
        },
        {
          "active": true,
          "defaultValue": false,
          "label": ">",
          "validFor": null,
          "value": ">"
        },
        {
          "active": true,
          "defaultValue": false,
          "label": "<=",
          "validFor": null,
          "value": "<="
        },
        {
          "active": true,
          "defaultValue": false,
          "label": ">=",
          "validFor": null,
          "value": ">="
        },
        {
          "active": true,
          "defaultValue": false,
          "label": "~=",
          "validFor": null,
          "value": "~="
        },
        {
          "active": true,
          "defaultValue": false,
          "label": "LIKE",
          "validFor": null,
          "value": "LIKE"
        },
        {
          "active": true,
          "defaultValue": false,
          "label": "NOT LIKE",
          "validFor": null,
          "value": "NOT LIKE"
        },
        {
          "active": true,
          "defaultValue": false,
          "label": "INCLUDES",
          "validFor": null,
          "value": "INCLUDES"
        },
        {
          "active": true,
          "defaultValue": false,
          "label": "EXCLUDES",
          "validFor": null,
          "value": "EXCLUDES"
        },
        {
          "active": true,
          "defaultValue": false,
          "label": "AND",
          "validFor": null,
          "value": "AND"
        },
        {
          "active": true,
          "defaultValue": false,
          "label": "OR",
          "validFor": null,
          "value": "OR"
        },
        {
          "active": true,
          "defaultValue": false,
          "label": "LIMIT",
          "validFor": null,
          "value": "LIMIT"
        },
        {
          "active": true,
          "defaultValue": false,
          "label": "OFFSET",
          "validFor": null,
          "value": "OFFSET"
        },
        {
          "active": true,
          "defaultValue": false,
          "label": "ORDER BY",
          "validFor": null,
          "value": "ORDER BY"
        },
        {
          "active": true,
          "defaultValue": false,
          "label": "IN",
          "validFor": null,
          "value": "IN"
        }
      ],
      "referenceTo": [],
      "relationshipName": null,
      "sortable": true,
      "type": "picklist"
    },
    {
      "aggregatable": true,
      "custom": false,
      "defaultValue": null,
      "extraTypeInfo": null,
      "filterable": true,
      "groupable": true,
      "inlineHelpText": null,
      "label": "Filter Value",
      "name": "FilterValue",
      "nillable": true,
      "picklistValues": [],
      "referenceTo": [],
      "relationshipName": null,
      "sortable": true,
      "type": "string"
    },
    {
      "aggregatable": false,
      "custom": false,
      "defaultValue": null,
      "extraTypeInfo": "plaintextarea",
      "filterable": false,
      "groupable": false,
      "inlineHelpText": null,
      "label": "Formula Converted",
      "name": "FormulaConverted",
      "nillable": true,
      "picklistValues": [],
      "referenceTo": [],
      "relationshipName": null,
      "sortable": false,
      "type": "textarea"
    },
    {
      "aggregatable": false,
      "custom": false,
      "defaultValue": null,
      "extraTypeInfo": "plaintextarea",
      "filterable": false,
      "groupable": false,
      "inlineHelpText": null,
      "label": "Formula Expression",
      "name": "FormulaExpression",
      "nillable": true,
      "picklistValues": [],
      "referenceTo": [],
      "relationshipName": null,
      "sortable": false,
      "type": "textarea"
    },
    {
      "aggregatable": true,
      "custom": false,
      "defaultValue": null,
      "extraTypeInfo": null,
      "filterable": true,
      "groupable": true,
      "inlineHelpText": null,
      "label": "Formula Result Path",
      "name": "FormulaResultPath",
      "nillable": true,
      "picklistValues": [],
      "referenceTo": [],
      "relationshipName": null,
      "sortable": true,
      "type": "string"
    },
    {
      "aggregatable": true,
      "custom": false,
      "defaultValue": null,
      "extraTypeInfo": null,
      "filterable": true,
      "groupable": false,
      "inlineHelpText": null,
      "label": "Formula Sequence",
      "name": "FormulaSequence",
      "nillable": true,
      "picklistValues": [],
      "referenceTo": [],
      "relationshipName": null,
      "sortable": true,
      "type": "double"
    },
    {
      "aggregatable": true,
      "custom": false,
      "defaultValue": null,
      "extraTypeInfo": null,
      "filterable": true,
      "groupable": true,
      "inlineHelpText": null,
      "label": "Global Key",
      "name": "GlobalKey",
      "nillable": true,
      "picklistValues": [],
      "referenceTo": [],
      "relationshipName": null,
      "sortable": true,
      "type": "string"
    },
    {
      "aggregatable": true,
      "custom": false,
      "defaultValue": null,
      "extraTypeInfo": null,
      "filterable": true,
      "groupable": true,
      "inlineHelpText": null,
      "label": "Input Object Name",
      "name": "InputObjectName",
      "nillable": true,
      "picklistValues": [],
      "referenceTo": [],
      "relationshipName": null,
      "sortable": true,
      "type": "string"
    },
    {
      "aggregatable": true,
      "custom": false,
      "defaultValue": null,
      "extraTypeInfo": null,
      "filterable": true,
      "groupable": false,
      "inlineHelpText": null,
      "label": "Input Object Query Sequence",
      "name": "InputObjectQuerySequence",
      "nillable": true,
      "picklistValues": [],
      "referenceTo": [],
      "relationshipName": null,
      "sortable": true,
      "type": "double"
    },
    {
      "aggregatable": false,
      "custom": false,
      "defaultValue": false,
      "extraTypeInfo": null,
      "filterable": true,
      "groupable": true,
      "inlineHelpText": null,
      "label": "Disabled",
      "name": "IsDisabled",
      "nillable": false,
      "picklistValues": [],
      "referenceTo": [],
      "relationshipName": null,
      "sortable": true,
      "type": "boolean"
    },
    {
      "aggregatable": false,
      "custom": false,
      "defaultValue": false,
      "extraTypeInfo": null,
      "filterable": true,
      "groupable": true,
      "inlineHelpText": null,
      "label": "Required For Upsert",
      "name": "IsRequiredForUpsert",
      "nillable": false,
      "picklistValues": [],
      "referenceTo": [],
      "relationshipName": null,
      "sortable": true,
      "type": "boolean"
    },
    {
      "aggregatable": false,
      "custom": false,
      "defaultValue": false,
      "extraTypeInfo": null,
      "filterable": true,
      "groupable": true,
      "inlineHelpText": null,
      "label": "Upsert Key",
      "name": "IsUpsertKey",
      "nillable": false,
      "picklistValues": [],
      "referenceTo": [],
      "relationshipName": null,
      "sortable": true,
      "type": "boolean"
    },
    {
      "aggregatable": true,
      "custom": false,
      "defaultValue": null,
      "extraTypeInfo": null,
      "filterable": true,
      "groupable": true,
      "inlineHelpText": null,
      "label": "Linked Field Name",
      "name": "LinkedFieldName",
      "nillable": true,
      "picklistValues": [],
      "referenceTo": [],
      "relationshipName": null,
      "sortable": true,
      "type": "string"
    },
    {
      "aggregatable": true,
      "custom": false,
      "defaultValue": null,
      "extraTypeInfo": null,
      "filterable": true,
      "groupable": false,
      "inlineHelpText": null,
      "label": "Linked Object Sequence",
      "name": "LinkedObjectSequence",
      "nillable": true,
      "picklistValues": [],
      "referenceTo": [],
      "relationshipName": null,
      "sortable": true,
      "type": "double"
    },
    {
      "aggregatable": true,
      "custom": false,
      "defaultValue": null,
      "extraTypeInfo": null,
      "filterable": true,
      "groupable": true,
      "inlineHelpText": null,
      "label": "Lookup By Field Name",
      "name": "LookupByFieldName",
      "nillable": true,
      "picklistValues": [],
      "referenceTo": [],
      "relationshipName": null,
      "sortable": true,
      "type": "string"
    },
    {
      "aggregatable": true,
      "custom": false,
      "defaultValue": null,
      "extraTypeInfo": null,
      "filterable": true,
      "groupable": true,
      "inlineHelpText": null,
      "label": "Lookup Object Name",
      "name": "LookupObjectName",
      "nillable": true,
      "picklistValues": [],
      "referenceTo": [],
      "relationshipName": null,
      "sortable": true,
      "type": "string"
    },
    {
      "aggregatable": true,
      "custom": false,
      "defaultValue": null,
      "extraTypeInfo": null,
      "filterable": true,
      "groupable": true,
      "inlineHelpText": null,
      "label": "Lookup Returned Field Name",
      "name": "LookupReturnedFieldName",
      "nillable": true,
      "picklistValues": [],
      "referenceTo": [],
      "relationshipName": null,
      "sortable": true,
      "type": "string"
    },
    {
      "aggregatable": true,
      "custom": false,
      "defaultValue": null,
      "extraTypeInfo": null,
      "filterable": true,
      "groupable": true,
      "inlineHelpText": null,
      "label": "Migration Attribute",
      "name": "MigrationAttribute",
      "nillable": true,
      "picklistValues": [],
      "referenceTo": [],
      "relationshipName": null,
      "sortable": true,
      "type": "string"
    },
    {
      "aggregatable": true,
      "custom": false,
      "defaultValue": null,
      "extraTypeInfo": null,
      "filterable": true,
      "groupable": true,
      "inlineHelpText": null,
      "label": "Migration Category",
      "name": "MigrationCategory",
      "nillable": true,
      "picklistValues": [],
      "referenceTo": [],
      "relationshipName": null,
      "sortable": true,
      "type": "string"
    },
    {
      "aggregatable": true,
      "custom": false,
      "defaultValue": null,
      "extraTypeInfo": null,
      "filterable": true,
      "groupable": true,
      "inlineHelpText": null,
      "label": "Migration Group",
      "name": "MigrationGroup",
      "nillable": true,
      "picklistValues": [],
      "referenceTo": [],
      "relationshipName": null,
      "sortable": true,
      "type": "string"
    },
    {
      "aggregatable": true,
      "custom": false,
      "defaultValue": null,
      "extraTypeInfo": null,
      "filterable": true,
      "groupable": true,
      "inlineHelpText": null,
      "label": "Migration Key",
      "name": "MigrationKey",
      "nillable": true,
      "picklistValues": [],
      "referenceTo": [],
      "relationshipName": null,
      "sortable": true,
      "type": "string"
    },
    {
      "aggregatable": true,
      "custom": false,
      "defaultValue": null,
      "extraTypeInfo": null,
      "filterable": true,
      "groupable": true,
      "inlineHelpText": null,
      "label": "Migration Pattern",
      "name": "MigrationPattern",
      "nillable": true,
      "picklistValues": [],
      "referenceTo": [],
      "relationshipName": null,
      "sortable": true,
      "type": "string"
    },
    {
      "aggregatable": true,
      "custom": false,
      "defaultValue": null,
      "extraTypeInfo": null,
      "filterable": true,
      "groupable": true,
      "inlineHelpText": null,
      "label": "Migration Process",
      "name": "MigrationProcess",
      "nillable": true,
      "picklistValues": [],
      "referenceTo": [],
      "relationshipName": null,
      "sortable": true,
      "type": "string"
    },
    {
      "aggregatable": true,
      "custom": false,
      "defaultValue": null,
      "extraTypeInfo": null,
      "filterable": true,
      "groupable": true,
      "inlineHelpText": null,
      "label": "Migration Type",
      "name": "MigrationType",
      "nillable": true,
      "picklistValues": [],
      "referenceTo": [],
      "relationshipName": null,
      "sortable": true,
      "type": "string"
    },
    {
      "aggregatable": true,
      "custom": false,
      "defaultValue": null,
      "extraTypeInfo": null,
      "filterable": true,
      "groupable": true,
      "inlineHelpText": null,
      "label": "Migration Value",
      "name": "MigrationValue",
      "nillable": true,
      "picklistValues": [],
      "referenceTo": [],
      "relationshipName": null,
      "sortable": true,
      "type": "string"
    },
    {
      "aggregatable": true,
      "custom": false,
      "defaultValue": null,
      "extraTypeInfo": null,
      "filterable": true,
      "groupable": false,
      "inlineHelpText": null,
      "label": "Output Creation Sequence",
      "name": "OutputCreationSequence",
      "nillable": true,
      "picklistValues": [],
      "referenceTo": [],
      "relationshipName": null,
      "sortable": true,
      "type": "double"
    },
    {
      "aggregatable": true,
      "custom": false,
      "defaultValue": null,
      "extraTypeInfo": null,
      "filterable": true,
      "groupable": true,
      "inlineHelpText": null,
      "label": "Output Field Format",
      "name": "OutputFieldFormat",
      "nillable": true,
      "picklistValues": [],
      "referenceTo": [],
      "relationshipName": null,
      "sortable": true,
      "type": "string"
    },
    {
      "aggregatable": true,
      "custom": false,
      "defaultValue": null,
      "extraTypeInfo": null,
      "filterable": true,
      "groupable": true,
      "inlineHelpText": null,
      "label": "Output Object Name",
      "name": "OutputObjectName",
      "nillable": true,
      "picklistValues": [],
      "referenceTo": [],
      "relationshipName": null,
      "sortable": true,
      "type": "string"
    },
    {
      "aggregatable": false,
      "custom": false,
      "defaultValue": null,
      "extraTypeInfo": "plaintextarea",
      "filterable": false,
      "groupable": false,
      "inlineHelpText": null,
      "label": "Transform Value Mappings",
      "name": "TransformValueMappings",
      "nillable": true,
      "picklistValues": [],
      "referenceTo": [],
      "relationshipName": null,
      "sortable": false,
      "type": "textarea"
    },
    {
      "aggregatable": true,
      "custom": false,
      "defaultValue": null,
      "extraTypeInfo": "plaintextarea",
      "filterable": true,
      "groupable": false,
      "inlineHelpText": null,
      "label": "Output Field Name",
      "name": "OutputFieldName",
      "nillable": true,
      "picklistValues": [],
      "referenceTo": [],
      "relationshipName": null,
      "sortable": true,
      "type": "textarea"
    },
    {
      "aggregatable": true,
      "custom": false,
      "defaultValue": null,
      "extraTypeInfo": "plaintextarea",
      "filterable": true,
      "groupable": false,
      "inlineHelpText": null,
      "label": "Input Field Name",
      "name": "InputFieldName",
      "nillable": true,
      "picklistValues": [],
      "referenceTo": [],
      "relationshipName": null,
      "sortable": true,
      "type": "textarea"
    }
  ],
  "label": "Omni Data Transformation Item",
  "childRelationships": [
    {
      "cascadeDelete": true,
      "childSObject": "AIInsightValue",
      "deprecatedAndHidden": false,
      "field": "SobjectLookupValueId",
      "junctionIdListNames": [],
      "junctionReferenceTo": [],
      "relationshipName": null,
      "restrictedDelete": false
    },
    {
      "cascadeDelete": false,
      "childSObject": "AIRecordInsight",
      "deprecatedAndHidden": false,
      "field": "TargetId",
      "junctionIdListNames": [],
      "junctionReferenceTo": [],
      "relationshipName": null,
      "restrictedDelete": false
    },
    {
      "cascadeDelete": false,
      "childSObject": "FlowExecutionErrorEvent",
      "deprecatedAndHidden": false,
      "field": "ContextRecordId",
      "junctionIdListNames": [],
      "junctionReferenceTo": [],
      "relationshipName": null,
      "restrictedDelete": false
    },
    {
      "cascadeDelete": false,
      "childSObject": "FlowRecordRelation",
      "deprecatedAndHidden": false,
      "field": "RelatedRecordId",
      "junctionIdListNames": [],
      "junctionReferenceTo": [],
      "relationshipName": null,
      "restrictedDelete": false
    }
  ],
  "custom": false,
  "name": "OmniDataTransformItem",
  "queryable": true
}